neuroplain/__init__.py
neuroplain/activation.py
neuroplain/ffnet.py
neuroplain/layer.py
neuroplain/losses.py
neuroplain-0.0.3.dist-info/LICENSE
neuroplain-0.0.3.dist-info/METADATA
neuroplain-0.0.3.dist-info/WHEEL
neuroplain-0.0.3.dist-info/top_level.txt
neuroplain-0.0.3.dist-info/RECORD
