Metadata-Version: 2.1
Name: neuroplain
Version: 0.0.3
Summary: Simple and easy to use neural networks library
Author-email: "Ioannis D (devcoons)" <support@devcoons.com>
License: MIT License
Project-URL: Homepage, https://github.com/devcoons/neuroplain
Project-URL: Issues, https://github.com/devcoons/neuroplain/issues
Keywords: neuroplain,neural networks
Classifier: Development Status :: 5 - Production/Stable
Classifier: Intended Audience :: Developers
Classifier: Natural Language :: English
Classifier: License :: OSI Approved :: MIT License
Classifier: Operating System :: OS Independent
Classifier: Programming Language :: Python :: 3.8
Classifier: Programming Language :: Python :: 3.9
Classifier: Programming Language :: Python :: 3.10
Classifier: Programming Language :: Python :: 3.11
Classifier: Programming Language :: Python :: 3.12
Classifier: Programming Language :: Python :: Implementation :: PyPy
Requires-Python: >=3.9
License-File: LICENSE
Requires-Dist: numpy >=1.26.0
Provides-Extra: dev
Requires-Dist: pip-tools ; extra == 'dev'
